{
    "BindCard_Gender_Female": "မ",
    "BindCard_Gender_Male": "က်ား",
    "Choose_Deposit_Time": "အခ်ိန္ သတ္မွတ္မည္",
    "Choose_Payment": "ေငြေၾကးထည့္ဝင္မည့္နည္းလမ္းကို ေ႐ြးခ်ယ္ပါ",
    "Continue_Pay": "ေပးေခ်မႈကို ဆက္လက္လုပ္ေဆာင္မည္",
    "Day": "{}",
    "Each_Day_In_Month_Deposit": "လစဥ္လတိုင္း၏ {}",
    "Each_WeekDay_Deposit": "{} တိုင္း",
    "ExposureInfo_Waiting_Wording": "ေက်းဇူးျပဳ၍ ေစာင့္ပါ...",
    "Fetch_Balance": "ထုတ္ယူႏိုင္သည့္ လက္က်န္ပမာဏ",
    "Fetch_Balance_Bank_Proccessing": "ဘဏ္သည္ လုပ္ငန္းလုပ္ေဆာင္ေနပါသည္",
    "Fetch_Balance_Open_Order": "ထုတ္ယူရန္အတြက္ ေတာင္းဆိုမည္",
    "Fetch_Balance_Success": "ေအာင္ျမင္စြာ ေရာက္ရွိပါသည္",
    "FillCard_Info_ErrorTips_Format": "{} ({} ခ်ိဳ႕ယြင္းခ်က္ စုစုေပါင္း)",
    "FillCard_Number_Default_Mobile_Modify_Tips": "အကယ္၍ မိုဘိုင္းလ္ နံပါတ္ မမွန္ကန္ပါက ျပင္ဆင္ရန္အတြက္ ႏွိပ္ပါ။",
    "FillCard_Number_Reg_Hint": "သင္၏ ဘဏ္ကတ္နံပါတ္",
    "FillCard_Number_Unreg_Hint": "___<BRAND>___ အေကာင့္ပိုင္ရွင္၏ ဘဏ္ကတ္နံပါတ္",
    "Friday": "ေသာၾကာ",
    "Give_Up": "စြန္႔လြတ္မည္",
    "LQT_Fixed_Deposit": "အႀကိမ္ႀကိမ္ ထည့္ဝင္မႈ",
    "LQT_Fixed_Deposit_Check_PWD_To_Add_Plan": "အႀကိမ္ႀကိမ္ထည့္ဝင္မႈကို လုပ္ေဆာင္ရန္ ေပးေခ်မႈစကားဝွက္ကို ထည့္သြင္းမည္",
    "LQT_Fixed_Deposit_Check_PWD_To_Delete_Plan": "အခ်ိန္ဇယားကို ဖ်က္ပစ္ရန္အတြက္ ေပးေခ်မႈစကားဝွက္ကို ထည့္သြင္းမည္",
    "LQT_Fixed_Deposit_Check_PWD_To_Pause_Plan": "အခ်ိန္ဇယားကို ရပ္ဆိုင္းရန္အတြက္ ေပးေခ်မႈစကားဝွက္ကို ထည့္သြင္းမည္",
    "LQT_Fixed_Deposit_Check_PWD_To_Start_Plan": "အခ်ိန္ဇယားကို စတင္လုပ္ေဆာင္ရန္ ေပးေခ်မႈစကားဝွက္ကို ထည့္သြင္းမည္",
    "LQT_Fixed_Deposit_Did_Delete": "ပယ္ဖ်က္ခဲ့သည္",
    "LQT_Fixed_Deposit_Did_Modify": "ေျပာင္းလဲထားပါသည္",
    "LQT_Fixed_Deposit_Did_Open": "ဖြင္႔ထားသည္",
    "LQT_Fixed_Deposit_Did_Pause": "ရပ္တန္႔ထားသည္",
    "LQT_Fixed_Deposit_No_Plan": "ထည့္သြင္းမႈ အခ်ိန္ဇယား မရွိပါ",
    "LQT_Fixed_Deposit_Plan": "ထည့္သြင္းမႈ အခ်ိန္ဇယား",
    "LQT_Fixed_Deposit_Plan_Set_Bank_Card_Tip": "အႀကိမ္ႀကိမ္ ထည့္ဝင္မႈကို သတ္မွတ္ရန္ ထည့္ဝင္ေငြမ်ားကို ျဖတ္ေတာက္ရန္အတြက္ ကတ္တစ္ကတ္ကို ဦးစြာေရြးခ်ယ္ပါ။",
    "LQT_Fixed_Deposit_Plan_Set_Time_Tip": "အႀကိမ္ႀကိမ္ ထည့္ဝင္မႈကို သတ္မွတ္ရန္ ေငြေၾကးထည့္ဝင္မည့္အခ်ိန္ကို ဦးစြာသတ္မွတ္ပါ။",
    "LQT_Fixed_Deposit_Plan_Should_Input": "အႀကိမ္ႀကိမ္ ထည့္ဝင္မႈကို သတ္မွတ္ရန္ ထည့္ဝင္မႈပမာဏကို ဦးစြာဝင္ေရာက္ပါ။",
    "ModifyPwdUseCase_ModifyPwd_Desc": "သြင္ျပင္လကၡဏာကို အတည္ျပဳရန္ ေပးေခ်မႈစကားဝွက္ကို ထည့္သြင္းပါ",
    "ModifyPwdUseCase_ModifyPwd_GiveUp_Title": "သင့္ေပးေခ်မႈစကားဝွက္အား ေျပာင္းလဲျခင္းကို ပယ္ဖ်က္မလား။",
    "ModifyPwdUseCase_ModifyPwd_Success": "စကားဝွက္ ေျပာင္းလဲၿပီးပါၿပီ",
    "ModifyPwdUseCase_ModifyPwd_Title": "စကားဝွက္ေျပာင္းမည္",
    "Monday": "တနၤလာ",
    "Monthly": "လစဥ္",
    "Saturday": "စေန",
    "Sunday": "တနဂၤေႏြ",
    "Thursday": "ၾကာသပေတး",
    "Tuesday": "အဂၤါ",
    "WCPay_BankCardBindTo0_0_5D_Detail": "ဤအေကာင့္ကို စစ္ေဆးအတည္ျပဳရန္ $0.05 ကို ေကာက္ခံမည္ျဖစ္ပါသည္",
    "WCPay_BankCardBindTo0_0_5D_Detail_back": "ဤအေကာင့္ကို စစ္ေဆးအတည္ျပဳရန္ $0.05 ကို ေကာက္ခံမည္ျဖစ္ၿပီး စစ္ေဆးမႈၿပီးသည့္ေနာက္တြင္ ေငြျပန္အမ္းပါမည္။",
    "WCPay_BankCardBindTo1B_Detail": "ဤအေကာင့္ကို စစ္ေဆးအတည္ျပဳရန¥0.01 ကို ေကာက္ခံမည္ျဖစ္ၿပီး စစ္ေဆးမႈၿပီးသည့္ေနာက္တြင္ ေငြျပန္အမ္းပါမည္။",
    "WCPay_BankCardBindTo1B_NotReturnDetail": "သင့္အေကာင့္ကို အသံုးျပဳႏိုင္ရန္အတြက္ စစ္ေဆးအတည္ျပဳရန္ ¥0.01 ကို ေကာက္ခံမည္ျဖစ္ပါသည္။",
    "WCPay_CountryCode_Title": "ႏိုင္ငံ/ေဒသ",
    "WCPay_FaceID_Auth_Tip": "ေငြေပးေခ်ရန္ သင့္မ်က္ႏွာကို အတည္ျပဳပါ",
    "WCPay_GiveUpReset_Title": "ေပးေခ်မႈစကားဝွက္ ျပန္လည္သတ္မွတ္ျခင္းကို ရပ္တန္႔မလား။",
    "WCPay_TouchID_Auth_Tip": "ေပးေခ်ရန္အတြက္ သိမ္းဆည္းၿပီး လက္ေဗြကို အတည္ျပဳပါ",
    "WCPay_TouchID_Confirm_Alert_Cancel": "ဖ်က္သိမ္းမည္",
    "WCPay_TouchID_Confirm_Alert_Content": "လက္ေဗြအတည္ျပဳၿပီးပါၿပီ။ ေပးေခ်မႈကို အတည္ျပဳမည္လား။ ",
    "WCPay_TouchID_Confirm_Alert_OK": "အတည္ျပဳရန္",
    "WCPay_TouchID_Confirm_Alert_Title": "ေပးေခ်မည္",
    "Wednesday": "ဗုဒၶဟူး",
    "Weekly": "အပတ္စဥ္",
    "address_item_key": "လိပ္စာ",
    "address_item_place_holder": "လိပ္စာ ထည့္သြင္းပါ",
    "agree": "သေဘာတူသည္",
    "agree_user_protocal": "အသံုးျပဳသူ သေဘာတူညီခ်က္ကို လက္ခံရန္",
    "agreement_alert": "ေက်းဇူးျပဳ၍ \"အသံုးျပဳသူ သေဘာတူညီခ်က္\" ကို ဦးစြာၾကည့္ရႈၿပီးမွ လက္ခံပါ။",
    "alertChargeFee": "ဝန္ေဆာင္ခ",
    "area_item_key": "ခရိုင္",
    "ask_verify_fingerprint": "လက္ေဗြကို အတည္ျပဳပါ",
    "assign_pay_dialog_content": "ထည့္သြင္းထားသည့္ ကိုယ္ေရးအခ်က္လက္မ်ားမွာ လက္ရွိခ်ိတ္ဆက္ထားသည့္ ___<BRAND>___ အေကာင့္မွ အခ်က္အလက္မ်ားႏွင့္ ကြာျခားေနပါသည္။ သင့္ဘဏ္ကဒ္ႏွင့္ခ်ိတ္ဆက္ထားသည့္ ___<BRAND>___ အေကာင့္ကို အသံုးျပဳၿပီး ထပ္မံအတည္ျပဳပါ။",
    "balance": "လက္က်န္ေငြ",
    "bank_card_item_key": "ဘဏ္ကဒ္",
    "bank_select_item_key": "ဘဏ္",
    "bind_new_card": "ဘဏ္ကဒ္အား ျဖည့္စြက္မည္",
    "bind_new_card_section_footer": "လံုျခံဳေရးအေၾကာင္းျခင္းရာမ်ားေၾကာင့္ ယခုခ်ိတ္ဆက္ထားေသာကဒ္အား ျဖဳတ္ပါမည္။",
    "bind_new_card_section_header": "ကဒ္အသစ္ခ်ိတ္ဆက္ၿပီး အေကာင့္အား ျပန္လည္အသက္သြင္းပါ",
    "bind_new_card_to_pay_tip": "ကိုယ္ေရးအခ်က္အလက္မွန္ကန္ေၾကာင္းအတည္ျပဳရန္ ေပးေခ်မႈစကားဝွက္ကို ထည့္သြင္းပါ",
    "bind_new_card_to_reset_mobile_desc": "ကဒ္အသစ္ထည့္၍ မိုဘုိင္းလ္ဖုန္းနံပါတ္တစ္ခုကို ခ်ိတ္ဆက္ပါ။",
    "binded_card_list_page_title": "SMS ျဖင့္ အတည္ျပဳရန္ ဖုန္းနံပါတ္ေရြးပါ",
    "birth_date_item_key": "ေမြးေန႔",
    "can_not_bind_more_card": "ခ်ိတ္ဆက္ႏိုင္သည့္ကတ္မ်ား အေရအတြက္ ျပည့္သြားပါၿပီ",
    "can_not_get_sms_with_question_mard_word": "အတည္ျပဳရန္Code ကို မရရွိဘဲျဖစ္ေနပါသလား။",
    "can_not_get_sms_word": "အတည္ျပဳရန္Code မရရွိခဲ့ပါ",
    "cancel_time": "ဖ်က္သိမ္းရန္အခ်ိန္ : {}",
    "cannot_receive_sms_code_content": "SMS ကုဒ္ကို သင့္ဘဏ္ႏွင့္ မွတ္ပံုတင္ထားေသာ သင့္မိုဘိုင္းလ္ နံပါတ္သို႔ ေပးပို႔ၿပီးျဖစ္သည္။ ဤမိုဘိုင္းလ္ နံပါတ္ကို လက္ရွိတြင္ သင္အသံုးျပဳေနရမည္ျဖစ္ၿပီး SMS ကုဒ္ကို မည္သည့္လံုျခံဳေရးအက္ပ္မ်ားကမွ မပိတ္ဆို႔ပါေစႏွင့္။ ဤမိုဘိုင္းလ္နံပါတ္အား ဆက္လက္အသံုးျပဳႏိုင္ျခင္းမရွိေတာ့လွ်င္ သင့္ဘဏ္ႏွင့္ ဆက္သြယ္ပါ။ အကူအညီမ်ားကို ပိုမို၍ ရယူလိုပါက Tencent သံုးစြဲသူဝန္ေဆာင္မႈဌာနသို႔ +86-0755-95017 မွတဆင့္ ဖုန္းေခၚဆိုပါ။",
    "cannot_receive_sms_code_title": "အတည္ျပဳရန္ကုဒ္ကို လက္ခံမရႏိုင္ပါ",
    "card_holder_dialog_content": "၁။ ရံပံုေငြမ်ား၏ လံုျခံဳေရးကို ေသခ်ာေစရန္အတြက္ ___<BRAND_ID>___ တစ္ခုလွ်င္ ဘဏ္ကတ္မ်ားကို နာမည္တူျဖင့္သာ ခ်ိတ္ဆက္ႏိုင္ပါသည္။\n\n၂။ အျခားနာမည္ျဖင့္ ခ်ိတ္ဆက္ရန္အတြက္ သင္၏ နာမည္မွန္ျဖစ္ေၾကာင္း အခ်က္အလက္ကို အပ္ဒိတ္လုပ္ရမည္ျဖစ္သည္။\n\n၃။ နာမည္မွန္ျဖစ္ေၾကာင္း အခ်က္အလက္ကို အပ္ဒိတ္လုပ္ၿပီးေနာက္တြင္ ကတ္ကိုင္ေဆာင္သူ၏ အခ်က္အလက္ေဟာင္းကို ဖ်က္သိမ္းမည္ျဖစ္ၿပီး ကတ္မ်ားကို ကတ္ကိုင္ေဆာင္သူ၏ နာမည္သစ္ျဖင့္ သင္ကသာ ေပါင္းထည့္ႏိုင္မည္ျဖစ္သည္။",
    "card_holder_dialog_title": "ကဒ္ေပၚမွအမည္",
    "card_holder_item_key": "ကဒ္ကိုင္ေဆာင္သူ",
    "card_holder_section_header": "ယခင္ကဘဏ္ကိုေပးထားသည့္ အခ်က္အလက္မ်ားအတိုင္း ထည့္သြင္းပါ။ ေနာင္တြင္ ယခုအမည္ႏွင့္မွတ္ပံုတင္ထားသည့္ ဘဏ္ကဒ္မ်ားကိုသာ ထည့္သြင္းႏိုင္မည္ျဖစ္သည္။",
    "card_info_section_header": "ကဒ္အခ်က္အလက္ ထည့္သြင္းပါ",
    "card_num_item_key": "ကဒ္နံပါတ္",
    "card_number_input_tips_title": "အခေၾကးေငြသို႔မဟုတ္ အြန္လိုင္းဘဏ္စနစ္မလိုအပ္ပါ။",
    "card_select_item_key": "ကဒ္အမ်ိဳးအစား",
    "card_type_section_header": "ကဒ္အမ်ိဳးအစား ေရြးခ်ယ္ရန္",
    "change_realname_word": "အမည္အစစ္ပာင္းလဲရန္",
    "change_to_face_id": "မ်က္ႏွာအသုံးျပဳ ေပးေခ်မႈ",
    "change_to_pwd": "စကားဝွက္ အသံုးျပဳရန္",
    "change_to_touch_id": "လက္ေဗြအသံုးျပဳရန္",
    "check_pay_pwd_page_desc": "မည္သူမည္ဝါျဖစ္ေၾကာင္းအတည္ျပဳရန္ ေပးေခ်မႈစကားဝွက္ကို ထည့္သြင္းပါ",
    "check_pay_pwd_page_title": "ကိုယ္ေရးအခ်က္အလက္အတည္ျပဳျခင္း",
    "check_sms_page_desc": "ဘဏ္ကဒ္ခ်ိတ္ဆက္ရန္ SMS ျဖင့္ အတည္ျပဳရန္ လိုအပ္သည္။ အတည္ျပဳရန္Code ကို ဖုန္း {} သို႔ ပို႔ၿပီးပါၿပီ။ လမ္းညြန္ခ်က္မ်ားအတိုင္း လုပ္ေဆာင္ပါ။",
    "check_sms_page_favor": "{}{:.2f} သင္သည္ ေပးေခ်ရလိမ့္မည္ (သက္သာ {}{:.2f})",
    "check_sms_page_title": "မိုဘုိင္းလ္ဖုန္းနံပါတ္ကို အတည္ျပဳမည္",
    "common_back": "ေနာက္သို႕",
    "common_cancel_word": "ဖ်က္သိမ္းမည္",
    "common_close": "ပိတ္မည္",
    "common_done_word": "ၿပီးဆံုးျပီ",
    "common_drop_out_word": "ထြက္ရန္",
    "common_i_know_word": "ရပါၿပ",
    "common_more": "ပိုမို၍",
    "common_next_word": "ေနာက္ထပ္",
    "common_question_word": "ေမးေလ႔ေမးထရွိေသာေမးခြန္းမ်ား",
    "common_select": "ေရြးခ်ယ္မည္",
    "common_tip_word": "သတိေပးခ်က္",
    "confirm_mobile_no": "မိုဘုိင္းဖုန္းအား အတည္ျပဳရန္",
    "confirm_pay": "ယခုေပးေခ်မည္",
    "confirm_to_receive": "လက္ခံရ႐ွိေၾကာင္း အတည္ျပဳပါ",
    "confrim_pay_and_open_deduct_word": "ေပးေခ်ၿပီး ဖြင့္ပါ",
    "confrim_pay_word": "ေပးေခ်မည္",
    "coupon_change_should_change_payment": "ေပးေခ်မႈ ပမာဏ ေျပာင္းလဲသြားပါသည္။ ျပန္လည္ေ႐ြးခ်ယ္ေပးပါ။",
    "coupon_component_need_bank_pay_tips": "အသိအမွတ္ျပဳၿပီးသည့္ ေပးေခ်မႈစနစ္အတြက္ ေလွ်ာ့ေစ်း",
    "cre_id_item_key": "ID နံပါတ္",
    "cre_id_item_place_holder": "ID ကဒ္နံပါတ္ ထည့္သြင္းပါ",
    "cre_type_item_key": "ID အမ်ိဳးအစား",
    "cre_type_item_place_holder": "အိုင္ဒီ အမ်ိဳးအစားေရြးခ်ယ္ရန္",
    "cvv_dialog_content": "သင့္ကဒ္၏ေနာက္ဖက္တြင္ ကဒ္အတည္ျပဳဂဏန္း ၃ လံုး သို႔မဟုတ္ ၄ လံုးရွိသည္။",
    "cvv_dialog_title": "ကဒ္အတည္ျပဳဂဏန္း ဆိုသည္မွာ အဘယ္နည္း။",
    "cvv_item_key": "ကဒ္အတည္ျပဳဂဏန္း ",
    "cvv_item_place_holder": "ပံုမွန္ဘဏ္ကဒ္၏ေနာက္တြင္ ဂဏန္း ၃ လံုး သို႕မဟုတ္ ၄ လံုး ပါရွိသည္",
    "default_delay_transfer_confirm_desc": "လႊဲေျပာင္းမႈသည္ {}နာရီအတြင္းေရာက္မည္",
    "email_item_key": "အီးေမး လိပ္စာ",
    "email_item_place_holder": "အီးေမးလ္ ထည့္သြင္းပါ",
    "error_detail_title": "ေျဖရွင္းနည္းကို ၾကည့္ရန္",
    "face_hongbao": "အနီးတဝုိက္ရွိ အထုပ္မ်ား",
    "fast_bind_card_support_bank_title_text": "လက္ရွိတြင္ ေအာက္ပါဘဏ္မ်ားအတြက္ ပံ့ပုိးေပးထားပါသည္",
    "fill_card_and_user_info_title": "ဘဏ္ကဒ္ႏွင့္ ကိုယ္ေရးအခ်က္အလက္မ်ား ျဖည့္ပါ",
    "fill_card_info_card_holder_assign_pay_header": "ေပးေခ်ရန္အတြက္ အသိအမွတ္ျပဳၿပီးသည့္ကဒ္ကို ကိုင္ေဆာင္သူ ျဖစ္ရမည္။",
    "fill_card_info_page_favor_desc": "{}{:.2f} အတြက္ ထပ္ေဆာင္းေခၽြတာရန္ ဤဘဏ္ကဒ္အမ်ိဳးအစားအား အသံုးျပဳပါ။",
    "fill_card_info_page_realname_cre_not_support": "ခ်ိတ္ဆက္ ရန္အတြက္ {} ကတ္ ကိုအသုံးမျပဳ ႏိုင္ပါ",
    "fill_card_info_page_title": "ကဒ္အခ်က္အလက္ ထည့္သြင္းပါ",
    "fill_card_num_format_error": "မမွန္ကန္သည့္ ကဒ္နံပါတ္",
    "fill_card_num_of_card_holder_section_header": "ကဒ္ကိုင္ေဆာင္သူ၏ ဘဏ္ကဒ္နံပါတ္ကို ထည့္သြင္းပါ",
    "fill_card_num_page_desc": "ဘဏ္ကဒ္ခ်ိတ္ဆက္ရန္",
    "fill_card_num_page_favor_dialog_title": "ဤကဒ္အား အသံုးျပဳ၍ ပိုမိုသက္သာစြာ အသံုးျပဳပါ",
    "fill_card_num_page_realname_desc": "အမည္မွန္ စိစစ္ျခင္းကို ျပည့္စံုေစရန္ သင့္ဘဏ္ကတ္ကို ထည့္သြင္းရမည္။",
    "fill_card_num_page_sns_input_hint": "ေပးေငြကဒ္မ်ားသာ အသံုးျပဳႏုိင္သည္",
    "fill_card_num_page_title": "ဘဏ္ကဒ္အား ျဖည့္စြက္မည္",
    "fill_card_number_assign_pay": "{} ၏ ဘဏ္ကဒ္ကိုအသံုးျပဳ၍ ေပးေခ်မည္",
    "fill_card_number_more_favor": "ေလ်ာ့ေစ်းမ်ားခံစားႏိုင္ရန္ အသိအမွတ္ျပဳၿပီးသည့္ ဘဏ္ကဒ္ကို အသံုးျပဳပါ။",
    "fill_complete_name": "နာမည္အျပည့္အစံု ထည့္သြင္းပါ",
    "fill_id_format_error": "ID နံပါတ္ပံုစံ မွားယြင္းေနပါသည္",
    "fill_in_sms_key": "အတည္ျပဳရန္Code",
    "fill_in_sms_word": "အတည္ျပဳရန္Codeကုိ ထည့္သြင္းပါ",
    "fill_phone_num_format_error": "မိုဘုိင္းဖုန္းနံပါတ္ပံုစံ မွားယြင္းေနပါသည္။",
    "finger_print_err_tips": "ျပန္လည္ၾကဳိးစားပါ",
    "first_name_item_key": "နာမည္အေရွ႕စာလံုး",
    "first_name_item_place_holder": "သင္၏အမည္ကို ထည့္သြင္းပါ",
    "float_paydesk_modal_no_select_favor": "အသံုးမျပဳရေသးသည့္ ေလ်ာ့ေစ်းမ်ား",
    "foreign_mobile_header": "မုိဘုိင္းဖုန္းနံပါတ္အသစ္ကုိ ထည့္သြင္းပါ",
    "forget_pay_pwd_title": "ေပးေခ်မႈစကားဝွက္ကို ေမ့ေလ်ာ့သြားခဲ့ သည္",
    "get_sms_with_count_down_word": "အတည္ျပဳရန္Code ရယူရန္ \n({})",
    "get_sms_word": "အတည္ျပဳရန္Codeကုိ ရယူပါ",
    "give_up_on_new_card": "ကဒ္ခ်ိတ္ဆက္ထားျခင္းကို ရပ္တန္႔မည္လား။",
    "give_up_this_order_or_not": "ယခုေငြေခ်မႈကို စြန္႔လြတ္မလား။",
    "group_aa": "ေဘလ္ခြဲထုတ္",
    "has_send_sms": "ေပးပို႕ၿပီးျဖစ္သည္",
    "has_send_sms_with_count": "ေပးပို႕ၿပီးျဖစ္သည္ ({})",
    "hongbao_refund_way_header_title": "ေပးပို႔ၿပီးသည့္ေနာက္ ၂၄ နာရီအတြင္း မဖြင့္ဘဲထားရွိသည့္ အန္ေပါင္းမ်ားကို ေအာက္ပါနည္းလမ္းျဖင့္ ေငြျပန္အမ္းပါလိမ့္မည္။",
    "hongbao_refund_way_title": "အန္ေပါင္းျပန္ထုတ္နည္း",
    "id_card_name": "ID ကဒ္",
    "install_cert_error": "အသိအမွတ္ျပဳလက္မွတ္ကို ထည့္သြင္းျခင္း မေအာင္ျမင္ပါ",
    "last_name_item_key": "နာမည္အေနာက္စာလံုး",
    "last_name_item_place_holder": "နာမည္အေနာက္စာလံုးအား ထည့္သြင္းပါ",
    "loading_title": "လုပ္ေဆာင္ေနသည္...",
    "lottery_network_error": "စိတ္မေကာင္းပါဘူး ေနာက္တစ္ႀကိမ္ ပို၍ကံေကာင္းပါေစ။",
    "lqt": "အေသးသံုးေငြ",
    "lqt_reset_mobile_desc": "ဘဏ္ကဒ္တစ္ခုကို ေရြးပါ။ ထိုကဒ္ဘဏ္ႏွင့္ခ်ိတ္ဆက္ထားသည့္ ဖုန္းနံပါတ္ကို အသံုးျပဳ၍ သင့္အေသးသံုးေငြကို အတည္ျပဳပါ။",
    "mobile_dialog_content": "သင့္ဘဏ္အေကာင့္ျဖင့္ မွတ္ပုံတင္ထားသည့္ မိုဘိုင္းလ္ နံပါတ္သည္ အေကာင့္ဖြင့္လွစ္သည့္အခါ ဘဏ္သို႔ သင္ပံ့ပိုးထားသည့္ နံပါတ္ျဖစ္ပါသည္။ သင္သည္ ဘဏ္သို႔ မိုဘိုင္းလ္ နံပါတ္တစ္ခုကို မပံ့ပိုးေပးခဲ့ပါက သင့္ေမ့ေလ်ာ့သည့္အခါျဖစ္ေစ ၎မိုဘိုင္းလ္ နံပါတ္ကို သင္ဆက္လက္အသံုးမျပဳႏိုင္ေတာ့သည့္အခါျဖစ္ေစ သင့္ဘဏ္ကို ဆက္သြယ္ၿပီး မိုဘိုင္းလ္ နံပါတ္ကို အပ္ဒိတ္လုပ္ပါ။",
    "mobile_dialog_title": "မိုဘိုင္းလ္ဖုန္း နံပါတ္မ်ား",
    "mobile_item_key": "မိုဘိုင္းလ္ဖုန္း နံပါတ္",
    "mobile_item_place_holder": "ဘဏ္ႏွင့္ခ်ိတ္ဆက္ထားသည့္ မိုဘုိင္းလ္ဖုန္းနံပါတ္အား ထည့္သြင္းပါ",
    "name_item_key": "အမည္",
    "name_item_place_holder": "ကဒ္ေပၚမွ နာမည္ကို ထည့္သြင္းပါ",
    "nationality_item_key": "ႏိုင္ငံ/ေဒသ",
    "nationality_place_holder": "ႏိုင္ငံ/ေဒသ ထည့္သြင္းပါ",
    "new_mobile_item_key": "မိုဘုိင္းလ္ဖုန္းနံပါတ္အသစ္",
    "new_mobile_item_place_holder": "ဘဏ္ႏွင့္ခ်ိတ္ဆက္ထားသည့္ မိုဘုိင္းလ္ဖုန္းနံပါတ္အား ထည့္သြင္းပါ",
    "new_user_card_num_input_safety_desc": "___<BRAND>___ အေကာင့္ပိုင္ရွင္ပိုင္ဆိုင္သည့္ကဒ္ကို ခ်ိတ္ဆက္ပါ",
    "new_user_card_num_input_safety_desc_v2": "___<BRAND>___ အေကာင့္ပိုင္ရွင္ပိုင္ဆိုင္သည့္ကဒ္ႏွင့္ ခ်ိတ္ဆက္ပါ",
    "no": "လက္မခံပါ",
    "offline_choose_payment": "ပုံေသ ေငြေပးေခ်နည္းကို ေ႐ြးခ်ယ္ရန္",
    "offline_choose_payment_fail": "သင္၏ ပုံေသ ေငြေခ်နည္း မေအာင္ျမင္ပါ၊ ေငြေပးေခ်မႈကို အၿပီးသတ္ရန္ အျခား နည္းလမ္းမ်ားကို လုပ္ေဆာင္ၾကည့္ပါမည္။",
    "offline_click_view_code": "ေငြေပးေခ်မႈကုဒ္နံပါတ္ကို ၾကည့္ရန္ ႏွိပ္ပါ",
    "offline_pay_modify_limit": "ပမာဏကို ျပင္ရန္",
    "offline_pay_only_pay_title": "ေပးမည္",
    "offline_pay_select_card_invalid": "ေ႐ြးခ်ယ္ထားေသာ ေငြေပးေခ်နည္းကို ေလာေလာဆယ္ သုံးမရႏုိင္ပါ။ တျခား ေငြေပးေခ်နည္းကို အသုံးျပဳၾကည့္ပါ။",
    "offline_pay_title": "ပုိက္ဆံ",
    "offline_pay_to_merchant": "ေရာင္းခ်သူမ်ားထံ ေပးေခ်မည္",
    "offline_prefer_payment": "ပုံေသ ေငြေပးေခ်နည္း",
    "offline_show_code_warning": "ေငြေပးေခ်ေသာအခါ ေငြကိုင္မ်ားကို ျပသရန္ ေငြေပးေခ်မႈ ကုဒ္နံပါတ္ကိုသာ အသုံးျပဳပါ။ သင္၏ လုံျခံဳေရးအတြက္ ၎အား မည္သူ႔ကိုမွ် မမွ်ေဝပါႏွင့္။",
    "offline_view_code_warning": "ေငြေပးေခ်ေသာအခါ ေငြကိုင္မ်ားကို ျပသရန္ ေငြေပးေခ်မႈ ကုဒ္နံပါတ္ကိုသာ အသုံးျပဳပါ။ သင္၏ လုံျခံဳေရးအတြက္ ၎အား မည္သူ႔ကိုမွ် မမွ်ေဝပါႏွင့္။",
    "ok": "အိုေက",
    "order_address_section_header": "ေငြေပးေခ်သည့္လိပ္စာ",
    "pay_card_detail_contact_user_info": "သံုးစြဲသူဝန္ေဆာင္မႈဌာနသို႕ဆက္သြယ္ရန္ : ",
    "pay_card_detail_tel_number": "၉၅၀၁၇",
    "pay_power_by_tenpay_word": "ယခုဝန္ေဆာင္မႈကို Tenpay မွ ေဆာင္ရြက္သည္",
    "pay_success": "ေငြေပးေခ်မႈ ေအာင္ျမင္သည္",
    "paydesk_coupon_page_title": "ေပးေခ်မႈေလ်ာ့ေစ်းမ်ားစာမ်က္ႏွာ",
    "paydesk_float_page_title": "စကားဝွက္",
    "paydesk_main_page_more_favor": "ေနာက္ထပ္ေလ်ာ့ေစ်းမ်ား",
    "paydesk_main_page_title": "ေပးေခ်မႈစာမ်က္ႏွာ",
    "paydesk_payment_page_title": "ေပးေခ်မႈကဒ္မ်ားစာရင္း",
    "paydesk_sub_page_title": "ေပးေခ်မႈ ထပ္တိုးစာမ်က္ႏွာ",
    "payee_remark_title": "ေပးေခ်သူ၏ မွတ္ခ်က္မ်ား",
    "paying_alert_tips": "ေပးေခ်မႈကို တင္သြင္းၿပီးျဖစ္ပါသည္။ ေပးေခ်မႈထပ္မံတင္သြင္းရန္ လိုအပ္ျခင္းရွိမရွိကို စစ္ေဆးရန္ ေပးေခ်မႈရလဒ္မက္ေဆ့ခ်္ကို ေစာင့္ပါ။",
    "payment_method": "ေပးေခ်မႈ နည္းလမ္း",
    "phone_number_item_key": "ဖုန္း",
    "phone_number_item_place_holder": "ဖုန္းနံပါတ္ ထည့္သြင္းပါ",
    "profession_item_key": "အလုပ္အကုိင္",
    "pure_bind_card_succ_tips": "ေအာင္ျမင္စြာ ခ်ိတ္ဆက္ၿပီးၿပီ",
    "pwd_repeat_error_tip": "စကားဝွက္မ်ား ကိုက္ညီမႈမရွိပါ",
    "rebind_bank_card_section_header": "သင့္အေကာင့္ျပန္လည္အသက္သြင္းရန္ ကဒ္ကိုေနာက္တစ္ႀကိမ္ခ်ိတ္ဆက္ပါ",
    "receipt": "ပုိက္ဆံ လက္ခံရယူပါ",
    "receive_done": "လက္ခံရ႐ွိထားသည္",
    "receive_remark_title": "ေငြလက္ခံမွတ္ခ်က္မ်ား",
    "receive_time": "လက္ခံရရွိခ်ိန္ : {}",
    "receiver_remark_title": "ေပးေခ်သူ၏ မွတ္ခ်က္မ်ား",
    "refund_doing_tip": "ေငြျပန္အမ္းမႈလုပ္ေဆာင္ျခင္း။ ၎ပမဏအား သင့္ကဒ္အတြင္း ရံုးဖြင့္ရက္ ၁ရက္မွ ၃ရက္ အတြင္း ျပန္အမ္းၿပီး ျဖစ္လိမ့္မည္။",
    "refund_done": "ေငြျပန္အမ္းၿပီး",
    "refund_done_and_expired": "ျပန္ေရာက္ခဲ့ၿပီး (သက္တမ္းလြန္)",
    "refund_time": "ျပန္ေရာက္သည့္အခ်ိန္ :{}",
    "refund_transfer_or_not": "{} မွျပန္လည္လႊဲေျပာင္းမည္လား။",
    "refund_word": "ျပန္သြားရန္",
    "renewal_time_item_key": "ေျပာင္းလဲခဲ့သည့္ အခ်ိန္",
    "resend_message_or_not": "ယခုမက္ေဆ့ခ်္ကို ထပ္မံေပးပို႕မည္လား။",
    "resend_sms": "ထပ္မံေပးပို႔ရန္",
    "resend_sms_with_count": "ျပန္လည္ေပးပို႔ရန္ ({})",
    "resend_success_tip": "မက္ေဆ့ခ်္ ျပန္လည္ေပးပို႕ၿပီးျဖစ္သည္",
    "resend_word": "ထပ္မံေပးပို႔ရန္",
    "reset_ban_mobile_fill_card_info_credit_tip_header": "ဘဏ္ကဒ္အခ်က္အလက္မ်ားစစ္ေဆးရန္ ထည့္သြင္းပါ",
    "reset_ban_mobile_fill_card_num_tip_header": "ဘဏ္ကဒ္အသစ္အား ျဖည့္စြက္ၿပီးေနာက္ ဘဏ္ႏွင့္ခ်ိတ္ဆက္ထားသည့္ မိုဘုိင္းလ္ဖုန္းနံပါတ္အသံုးျပဳ၍ ေပးေခ်မႈလက္က်န္ေငြမ်ားကို စစ္ေဆးပါ။",
    "reset_cvv_and_valid_date_tip": "သင္သည္ ခ်ိတ္ဆက္ထားသည့္ ကဒ္အခ်က္အလက္မ်ားအား ျပင္ဆင္ၿပီး ေပးေခ်မႈကိုလည္း တစ္ပါတည္း ျပဳလုပ္ေနပါသည္။ အကယ္၍ သင္သည္ တစ္စံုတစ္ရာႏွင့္ ပတ္သက္၍ ေသခ်ာမႈမရွိလွ်င္ သင့္ဘဏ္၏ သံုးစြဲသူဝန္ေဆာင္မႈဌာနသို႔ ဆက္သြယ္ပါ။ ",
    "reset_cvv_title": "ကဒ္အတည္ျပဳဂဏန္း ေျပာင္းလဲရန္",
    "reset_lqt_mobile_fill_card_num_tip_header": "ကဒ္အသစ္အား ျဖည့္စြက္ၿပီး ၎ကဒ္၏ မွတ္ပံုတင္ထားသည့္ မိုဘုိင္းဖုန္းနံပါတ္ကို အသံုးျပဳ၍ အေသးသံုးေငြ SMS အတည္ျပဳခ်က္ကို ေဆာင္ရြက္ပါ။",
    "reset_mobile_bank_card_number": "ကတ္",
    "reset_mobile_card_desc_format": "{}{} ({}) မွတ္ပံုတင္ထားသည့္ မိုဘိုင္းဖုန္းနံပါတ္",
    "reset_mobile_card_desc_with_update_format": "{}{} ({}) မွတ္ပံုတင္ထားသည့္ မိုဘိုင္းဖုန္းနံပါတ္။ ",
    "reset_mobile_new_mobile_info_btn": "အေသးစိတ္အခ်က္မ်ား",
    "reset_mobile_new_mobile_number": "မိုဘိုင္းလ္ဖုန္းနံပါတ္ အသစ္",
    "reset_mobile_phone_page_title": "မိုဘုိင္းဖုန္းနံပါတ္ကို တည္းျဖတ္ရန္",
    "reset_phone_tip": "ကိုယ္ေရးအခ်က္အလက္အတည္ျပဳၿပီးလွ်င္ ေပးေခ်မႈျပဳလုပ္ႏုိင္ပါသည္။ သင့္ဘဏ္ႏွင့္ခ်ိတ္ဆက္ထားသည့္ဖုန္းနံပါတ္အား အတည္ျပဳရန္ ကိုေခၚပါ ",
    "reset_pwd_fill_rebind_card_info_page_title": "ဘဏ္ကဒ္အခ်က္အလက္မ်ား ထည့္သြင္းပါ",
    "reward": "ဆုလဒ္ကုဒ္",
    "safety_dialog_content": "လံုျခံဳေရးဆိုင္ရာ အေရးယူေဆာင္ရြက္မႈမ်ား : အေကာင့္ကာကြယ္ျခင္း၊ အခ်ိန္ျပည့္ေစာင့္ၾကည့္ျခင္း၊ အေရးေပၚရပ္တန္႕ျခင္း။ \n\n ႏွစ္ဆင့္အတည္ျပဳျခင္း : သင့္ပးေခ်မႈစကားဝွက္သည္ ေပးေခ်မႈတိုင္းအတြက္ လိုအပ္သည္။ ပမာဏမ်ားသည့္ပးေခ်မႈမ်ားအတြက္ SMS ျဖင့္ အတည္ျပဳရန္ လိုအပ္သည္။ \n\nအခ်က္အလက္ကာကြယ္ျခင္း : အသံုးျပဳသူအခ်က္လက္မ်ားအား ကာကြယ္ရန္ ခိုင္မာသည့္ အခ်က္အလက္ထိန္းခ်ဳပ္မႈနည္းပညာကို အသံုးျပဳထားသည္။ \n\nေပးေခ်မႈအာမခံ : ေပးေခ်မႈမ်ားကို PICC မွ အာမခံထားပါသည္။",
    "safety_dialog_title": "လံုျခံဳေရးကာကြယ္မႈမ်ား",
    "scan_card_num_title": "ကတ္ကို စကန္ဖတ္ရန္",
    "select_payment": "ေပးေခ်မႈ နည္းလမ္းကို ေရြးပါ",
    "select_payment_card": "ႀကိဳက္ႏွစ္သက္သည့္ ေငြေပးေခ်မႈစနစ္ကို ေ႐ြးပါ",
    "send_verify_code_btn_wording": "ပို႕မည္",
    "send_verify_code_switch_btn_wording": "အတည္ျပဳစနစ္အား ေျပာင္းလဲရန္",
    "send_verify_code_tips_format": "SMS အတည္ျပဳရန္Codeကို : \n{} သို႕ပို႕မည္",
    "set_pay_pwd_confirm_page_title": "အတည္ျပဳရန္ ထပ္မံထည့္သြင္းပါ",
    "set_pay_pwd_page_desc": "ေပးေခ်မႈမ်ားအား အတည္ျပဳႏိုင္ရန္ ___<BRAND_Pay>___ စကားဝွက္ သတ္မွတ္မည္",
    "set_pay_pwd_page_title": "ေပးေခ်မႈစကားဝွက္ကို ခ်ိန္ညွိမည္",
    "set_pwd_success": "ခ်ိန္ညႇိမွုမ်ား ျပင္ဆင္ၿပီးပါၿပီ",
    "succ_page_open_biometric_cancel_btn_title": "ယခုမဟုတ္ပါ",
    "succ_page_open_biometric_dialog_content": "ေပးေခ်မႈမ်ား ပိုမိုျမန္ဆန္ေစရန္ မ်က္ႏွာ သို႔မဟုတ္ လက္ေဗြေပးေခ်မႈစနစ္ကို ဖြင့္ႏိုင္ပါသည္။",
    "succ_page_open_biometric_faceid_btn_title": "မ်က္ႏွာအသံုးျပဳေငြေခ်စနစ္",
    "succ_page_open_biometric_touchid_btn_title": "လက္ေဗြေပးေခ်မႈစနစ္",
    "succ_page_open_face_id_dialog_content": "ေပးေခ်မႈမ်ား ပိုမိုျမန္ဆန္ေစရန္ႏွင့္ လံုျခံဳမႈရွိေစရန္ မ်က္ႏွာမွတ္သားစနစ္ အသံုးျပဳရန္အတြက္ မ်က္ႏွာအသံုးျပဳေငြေခ်စနစ္ကို ဖြင့္ပါ။",
    "succ_page_open_face_id_right_btn_title": "မ်က္ႏွာအသံုးျပဳေငြေခ်စနစ္ကို ဖြင့္ပါ",
    "succ_page_open_touch_id_dialog_content": "ေပးေခ်မႈမ်ား ပိုမိုျမန္ဆန္ေစရန္ႏွင့္ လံုျခံဳမႈရွိေစရန္ လက္ေဗြမွတ္စနစ္ အသံုးျပဳရန္အတြက္ ထိေတြ႕ေပးေခ်မႈစနစ္ကို ဖြင့္ပါ",
    "succ_page_open_touch_id_left_btn_title": "ေနာက္တစ္ခါမွ စဥ္းစားမည္",
    "succ_page_open_touch_id_right_btn_title": "ထိေတြ႕ေပးေခ်မႈစနစ္ကို ဖြင့္ပါ။",
    "to_be_confirm_receive": "လက္ခံရရွိေၾကာင္း အတည္မျပဳရေသးပါ",
    "transfer": "လႊဲေျပာင္းမည္",
    "transfer_account": "လႊဲေျပာင္းသည့္ပမာဏ",
    "transfer_amount_input_invalid_hint": "ျဖည့္သြင္းထားသည့္ပမာဏ မွားယြင္းေနပါသည္",
    "transfer_bank": "ဘဏ္ကတ္သို႔ ေငြလႊဲပါ",
    "transfer_explain": "လႊဲေျပာင္းမည့္မွတ္ခ်က္အား ျဖည့္စြက္မည္",
    "transfer_modify_explain": "ေျပာင္းလဲမည္",
    "transfer_second_left_button": "ဖ်က္သိမ္းမည္",
    "transfer_second_right_button": "ေရွ႕ဆက္ရန္",
    "transfer_second_title": "လႊဲေျပာင္းမႈ သတိေပးခ်က္",
    "transfer_time": "လႊဲေျပာင္းခ်ိန္ :{}",
    "transfer_ui_title": "သူငယ္ခ်င္းထံသို႔ လႊဲေျပာင္းမည္",
    "understand_safety": "လံုျခံဳေရးကာကြယ္မႈမ်ား",
    "update_word": "ျပင္ဆင္ရန္",
    "user_card_type_select_placeholder_v2": "ဘဏ္ကတ္ႏွင့္ ကတ္အမ်ိဳးအစားကို ေရြးခ်ယ္ပါ",
    "user_info_section_header": "ကုိယ္ေရးအခ်က္အလက္ကုိ ထည့္သြင္းပါ",
    "user_protocal": "\"အသံုးျပဳသူ သေဘာတူညီခ်က္\"",
    "valid_date_item_key": "သက္တမ္းကုန္ဆံုးျခင္း",
    "verify_cre_tip": "ကိုယ္ေရးအခ်က္အလက္အတည္ျပဳရန္္ {} ၏ {} မွ ေနာက္ဆံုးဂဏန္း ၄ လံုးကိုထည့္သြင္းပါ",
    "verify_fingerprint_fail": "လက္ေဗြအတည္ျပဳျခင္း မေအာင္ျမင္ပါ",
    "verify_id_ui_true_name_tips": "{} (အမည္အျပည့္အစံုကို ရိုက္ထည့္ပါ)",
    "wechat_bank_agreement": "ဘဏ္သေဘာတူညီမႈ",
    "wechat_mobile_phone_word": "မိုဘုိင္းလ္ဖုန္းကို ___<BRAND>___ သုိ႔ေအာင္ျမင္စြာ ခ်ိတ္ဆက္ၿပီးပါၿပီ။",
    "wechat_user_agreement": "Weixin Pay အသံုးျပဳသူသေဘာတူညီခ်က္",
    "wxp_common_cancel": "ဖ်က္သိမ္းမည္",
    "wxp_common_confirm": "အိုေက",
    "wxp_common_i_know": "ရပါၿပီ",
    "wxp_common_remind": "သတိေပးခ်က္",
    "wxp_network_error": "စနစ္အလုပ္မ်ားေနပါသည္။ ေနာက္မွ ထပ္မံႀကိဳးစားပါ။",
    "wxp_payment_network_error": "လႊဲေျပာင္းမႈအား တင္သြင္းၿပီးျဖစ္သည္။ ေပးေခ်မႈအေျခအေနဆိုင္ရာ အသိေပးခ်က္ကို ___<BRAND_Pay>___ တရားဝင္အေကာင့္တြင္ လက္ခံရရွိပါမည္။ လိုအပ္ပါက ေပးေခ်မႈအား ေနာက္ထပ္မတင္သြင္းမီ ေပးေခ်မႈအေျခအေနကို အတည္ျပဳပါ။",
    "wxp_system_error": "စနစ္အလုပ္မ်ားေနပါသည္။ ေနာက္မွ ထပ္မံႀကိဳးစားပါ။",
    "wxp_wcpay_system_error": "စနစ္အလုပ္မ်ားေနပါသည္။ ေနာက္မွ ထပ္မံႀကိဳးစားပါ။",
    "yes": "လက္ခံသည္",
    "zip_item_key": "စာတိုက္ကုဒ္",
    "zip_item_place_holder": "စာတိုက္ကုဒ္ ထည့္သြင္းပါ"
}