{"v":"4.6.10","fr":25,"ip":0,"op":26,"w":60,"h":60,"nm":"white","ddd":0,"assets":[{"id":"comp_0","layers":[{"ddd":0,"ind":1,"ty":4,"nm":"Rectangle 339","ks":{"o":{"a":0,"k":100},"r":{"a":0,"k":0},"p":{"a":0,"k":[301,202,0]},"a":{"a":0,"k":[0,20,0]},"s":{"a":0,"k":[100,100,100]}},"ao":0,"shapes":[{"ty":"gr","it":[{"ty":"rc","d":1,"s":{"a":1,"k":[{"i":{"x":[0.833,0.833],"y":[0.833,0.833]},"o":{"x":[0.167,0.167],"y":[0.167,0.167]},"n":["0p833_0p833_0p167_0p167","0p833_0p833_0p167_0p167"],"t":12,"s":[4,0],"e":[4,8]},{"i":{"x":[0.833,0.833],"y":[0.833,0.833]},"o":{"x":[0.167,0.167],"y":[0.167,0.167]},"n":["0p833_0p833_0p167_0p167","0p833_0p833_0p167_0p167"],"t":17,"s":[4,8],"e":[4,8]},{"t":19}]},"p":{"a":1,"k":[{"i":{"x":0.833,"y":0.833},"o":{"x":0.167,"y":0.167},"n":"0p833_0p833_0p167_0p167","t":12,"s":[0,5],"e":[0,-1],"to":[0,-1],"ti":[0,0.83333331346512]},{"i":{"x":0.833,"y":0.833},"o":{"x":0.167,"y":0.167},"n":"0p833_0p833_0p167_0p167","t":17,"s":[0,-1],"e":[0,0],"to":[0,-0.83333331346512],"ti":[0,-0.16666667163372]},{"t":19}]},"r":{"a":0,"k":100},"nm":"矩形路径 1","mn":"ADBE Vector Shape - Rect"},{"ty":"fl","c":{"a":0,"k":[1,1,1,1]},"o":{"a":0,"k":100},"r":1,"nm":"填充 1","mn":"ADBE Vector Graphic - Fill"},{"ty":"tr","p":{"a":0,"k":[0,0],"ix":2},"a":{"a":0,"k":[0,0],"ix":1},"s":{"a":0,"k":[500,500],"ix":3},"r":{"a":0,"k":0,"ix":6},"o":{"a":0,"k":100,"ix":7},"sk":{"a":0,"k":0,"ix":4},"sa":{"a":0,"k":0,"ix":5},"nm":"变换"}],"nm":"Rectangle 50","np":2,"cix":2,"ix":1,"mn":"ADBE Vector Group"}],"ip":0,"op":500,"st":0,"bm":0,"sr":1},{"ddd":0,"ind":2,"ty":4,"nm":"Rectangle 50","ks":{"o":{"a":1,"k":[{"i":{"x":[0.833],"y":[0.833]},"o":{"x":[0.167],"y":[0.167]},"n":["0p833_0p833_0p167_0p167"],"t":7,"s":[100],"e":[0]},{"t":12}]},"r":{"a":0,"k":0},"p":{"a":0,"k":[301,202,0]},"a":{"a":0,"k":[0,20,0]},"s":{"a":0,"k":[100,100,100]}},"ao":0,"shapes":[{"ty":"gr","it":[{"ty":"rc","d":1,"s":{"a":1,"k":[{"i":{"x":[0.833,0.833],"y":[0.833,0.833]},"o":{"x":[0.167,0.167],"y":[0.167,0.167]},"n":["0p833_0p833_0p167_0p167","0p833_0p833_0p167_0p167"],"t":5,"s":[4,8],"e":[4,8]},{"i":{"x":[0.833,0.833],"y":[0.833,0.833]},"o":{"x":[0.167,0.167],"y":[0.167,0.167]},"n":["0p833_0p833_0p167_0p167","0p833_0p833_0p167_0p167"],"t":7,"s":[4,8],"e":[4,4]},{"t":12}]},"p":{"a":1,"k":[{"i":{"x":0.833,"y":0.833},"o":{"x":0.167,"y":0.167},"n":"0p833_0p833_0p167_0p167","t":5,"s":[0,0],"e":[0,-4],"to":[0,-0.66666668653488],"ti":[0,1]},{"i":{"x":0.833,"y":0.833},"o":{"x":0.167,"y":0.167},"n":"0p833_0p833_0p167_0p167","t":7,"s":[0,-4],"e":[0,-6],"to":[0,-1],"ti":[0,0.33333334326744]},{"t":12}]},"r":{"a":0,"k":100},"nm":"矩形路径 1","mn":"ADBE Vector Shape - Rect"},{"ty":"fl","c":{"a":0,"k":[1,1,1,1]},"o":{"a":0,"k":100},"r":1,"nm":"填充 1","mn":"ADBE Vector Graphic - Fill"},{"ty":"tr","p":{"a":0,"k":[0,0],"ix":2},"a":{"a":0,"k":[0,0],"ix":1},"s":{"a":0,"k":[500,500],"ix":3},"r":{"a":0,"k":0,"ix":6},"o":{"a":0,"k":100,"ix":7},"sk":{"a":0,"k":0,"ix":4},"sa":{"a":0,"k":0,"ix":5},"nm":"变换"}],"nm":"Rectangle 50","np":2,"cix":2,"ix":1,"mn":"ADBE Vector Group"}],"ip":0,"op":500,"st":0,"bm":0,"sr":1}]}],"layers":[{"ddd":0,"ind":1,"ty":0,"nm":"line","refId":"comp_0","ks":{"o":{"a":0,"k":100},"r":{"a":0,"k":0},"p":{"a":0,"k":[29.812,32.625,0]},"a":{"a":0,"k":[300,300,0]},"s":{"a":0,"k":[20,20,100]}},"ao":0,"w":600,"h":600,"ip":0,"op":500,"st":0,"bm":0,"sr":1},{"ddd":0,"ind":2,"ty":0,"nm":"line","refId":"comp_0","ks":{"o":{"a":0,"k":100},"r":{"a":0,"k":45},"p":{"a":0,"k":[28.688,31.062,0]},"a":{"a":0,"k":[300,300,0]},"s":{"a":0,"k":[20,20,100]}},"ao":0,"w":600,"h":600,"ip":0,"op":500,"st":0,"bm":0,"sr":1},{"ddd":0,"ind":3,"ty":0,"nm":"line","refId":"comp_0","ks":{"o":{"a":0,"k":100},"r":{"a":0,"k":-45},"p":{"a":0,"k":[30.062,31.312,0]},"a":{"a":0,"k":[300,300,0]},"s":{"a":0,"k":[20,20,100]}},"ao":0,"w":600,"h":600,"ip":0,"op":500,"st":0,"bm":0,"sr":1},{"ddd":0,"ind":4,"ty":4,"nm":"Combined Shape","ks":{"o":{"a":0,"k":100},"r":{"a":0,"k":0},"p":{"a":0,"k":[95.5,118.622,0]},"a":{"a":0,"k":[82.5,102.575,0]},"s":{"a":0,"k":[100,100,100]}},"ao":0,"shapes":[{"ty":"gr","it":[{"ty":"gr","it":[{"ind":0,"ty":"sh","ix":1,"ks":{"a":0,"k":{"i":[[-3.64,-2.27],[0,-1.47],[0,0],[-1.06,0],[0,0],[0,1.07],[0,0],[-1.31,0.69],[0,4.36],[6.9,0],[0,-6.9]],"o":[[1.29,0.69],[0,0],[0,1.07],[0,0],[1.06,0],[0,0],[0,-1.48],[3.64,-2.27],[0,-6.9],[-6.9,0],[0,4.36]],"v":[[5.89,23.11],[7.999,26.63],[7.999,30.03],[9.919,31.96],[15.073,31.96],[17.003,30.03],[17.003,26.65],[19.11,23.11],[25,12.5],[12.5,0],[0,12.5]],"c":true}},"nm":"路径 1","mn":"ADBE Vector Shape - Group"},{"ty":"tr","p":{"a":0,"k":[4,4],"ix":2},"a":{"a":0,"k":[0,0],"ix":1},"s":{"a":0,"k":[100,100],"ix":3},"r":{"a":0,"k":0,"ix":6},"o":{"a":0,"k":100,"ix":7},"sk":{"a":0,"k":0,"ix":4},"sa":{"a":0,"k":0,"ix":5},"nm":"变换"}],"nm":"Path","np":1,"cix":2,"ix":1,"mn":"ADBE Vector Group"},{"ty":"gr","it":[{"ind":0,"ty":"sh","ix":1,"ks":{"a":0,"k":{"i":[[0,0],[0,0],[0,5.72],[-9.11,0],[0,-9.11],[4.82,-3.02],[0,0],[0,0],[0,0],[3.27,0],[0,0],[0,3.28],[0,0]],"o":[[0,0],[-4.82,-3.02],[0,-9.11],[9.11,0],[0,5.72],[0,0],[0,0],[0,0],[0,3.28],[0,0],[-3.27,0],[0,0],[0,0]],"v":[[7.88,30.57],[7.76,30.5],[0,16.5],[16.5,0],[33,16.5],[25.24,30.5],[25.12,30.58],[24.99,30.64],[24.99,34.002],[19.06,39.932],[13.92,39.932],[8,34.002],[8,30.63]],"c":true}},"nm":"路径 1","mn":"ADBE Vector Shape - Group"},{"ty":"tr","p":{"a":0,"k":[0,0],"ix":2},"a":{"a":0,"k":[0,0],"ix":1},"s":{"a":0,"k":[100,100],"ix":3},"r":{"a":0,"k":0,"ix":6},"o":{"a":0,"k":100,"ix":7},"sk":{"a":0,"k":0,"ix":4},"sa":{"a":0,"k":0,"ix":5},"nm":"变换"}],"nm":"Path","np":1,"cix":2,"ix":2,"mn":"ADBE Vector Group"},{"ty":"mm","mm":1,"nm":"合并路径 1","mn":"ADBE Vector Filter - Merge"},{"ty":"fl","c":{"a":0,"k":[1,1,1,1]},"o":{"a":0,"k":100},"r":1,"nm":"填充 1","mn":"ADBE Vector Graphic - Fill"},{"ty":"tr","p":{"a":0,"k":[0,0],"ix":2},"a":{"a":0,"k":[0,0],"ix":1},"s":{"a":0,"k":[100,100],"ix":3},"r":{"a":0,"k":0,"ix":6},"o":{"a":0,"k":100,"ix":7},"sk":{"a":0,"k":0,"ix":4},"sa":{"a":0,"k":0,"ix":5},"nm":"变换"}],"nm":"Combined Shape","np":4,"cix":2,"ix":1,"mn":"ADBE Vector Group"}],"ip":0,"op":500,"st":0,"bm":0,"sr":1},{"ddd":0,"ind":5,"ty":4,"nm":"Rectangle 337","ks":{"o":{"a":0,"k":100},"r":{"a":0,"k":0},"p":{"a":0,"k":[27.375,37.375,0]},"a":{"a":0,"k":[0,0,0]},"s":{"a":0,"k":[100,100,100]}},"ao":0,"shapes":[{"ty":"gr","it":[{"ty":"rc","d":1,"s":{"a":0,"k":[9,3]},"p":{"a":0,"k":[0,0]},"r":{"a":0,"k":100},"nm":"矩形路径 1","mn":"ADBE Vector Shape - Rect"},{"ty":"fl","c":{"a":0,"k":[1,1,1,1]},"o":{"a":0,"k":100},"r":1,"nm":"填充 1","mn":"ADBE Vector Graphic - Fill"},{"ty":"tr","p":{"a":0,"k":[0,0],"ix":2},"a":{"a":0,"k":[0,0],"ix":1},"s":{"a":0,"k":[100,100],"ix":3},"r":{"a":0,"k":45,"ix":6},"o":{"a":0,"k":100,"ix":7},"sk":{"a":0,"k":0,"ix":4},"sa":{"a":0,"k":0,"ix":5},"nm":"变换"}],"nm":"Rectangle 337","np":2,"cix":2,"ix":1,"mn":"ADBE Vector Group"}],"ip":0,"op":500,"st":0,"bm":0,"sr":1},{"ddd":0,"ind":6,"ty":4,"nm":"Rectangle 338","ks":{"o":{"a":0,"k":100},"r":{"a":0,"k":0},"p":{"a":0,"k":[31.625,37.375,0]},"a":{"a":0,"k":[0,0,0]},"s":{"a":0,"k":[-100,100,100]}},"ao":0,"shapes":[{"ty":"gr","it":[{"ty":"rc","d":1,"s":{"a":0,"k":[9,3]},"p":{"a":0,"k":[0,0]},"r":{"a":0,"k":100},"nm":"矩形路径 1","mn":"ADBE Vector Shape - Rect"},{"ty":"fl","c":{"a":0,"k":[1,1,1,1]},"o":{"a":0,"k":100},"r":1,"nm":"填充 1","mn":"ADBE Vector Graphic - Fill"},{"ty":"tr","p":{"a":0,"k":[0,0],"ix":2},"a":{"a":0,"k":[0,0],"ix":1},"s":{"a":0,"k":[100,100],"ix":3},"r":{"a":0,"k":45,"ix":6},"o":{"a":0,"k":100,"ix":7},"sk":{"a":0,"k":0,"ix":4},"sa":{"a":0,"k":0,"ix":5},"nm":"变换"}],"nm":"Rectangle 337","np":2,"cix":2,"ix":1,"mn":"ADBE Vector Group"}],"ip":0,"op":500,"st":0,"bm":0,"sr":1},{"ddd":0,"ind":7,"ty":4,"nm":"light","ks":{"o":{"a":1,"k":[{"i":{"x":[0.833],"y":[0.833]},"o":{"x":[0.167],"y":[0.167]},"n":["0p833_0p833_0p167_0p167"],"t":5,"s":[100],"e":[0]},{"t":18}]},"r":{"a":0,"k":0},"p":{"a":0,"k":[29.5,32.5,0]},"a":{"a":0,"k":[0,0,0]},"s":{"a":1,"k":[{"i":{"x":[0.833,0.833,0.833],"y":[0.833,0.833,0.833]},"o":{"x":[0.167,0.167,0.167],"y":[0.167,0.167,0.167]},"n":["0p833_0p833_0p167_0p167","0p833_0p833_0p167_0p167","0p833_0p833_0p167_0p167"],"t":5,"s":[0,0,100],"e":[100,100,100]},{"t":18}]}},"ao":0,"shapes":[{"ty":"gr","it":[{"d":1,"ty":"el","s":{"a":0,"k":[270,270]},"p":{"a":0,"k":[0,0]},"nm":"椭圆路径 1","mn":"ADBE Vector Shape - Ellipse"},{"ty":"fl","c":{"a":0,"k":[1,0.8527574,0,1]},"o":{"a":0,"k":100},"r":1,"nm":"填充 1","mn":"ADBE Vector Graphic - Fill"},{"ty":"tr","p":{"a":0,"k":[0,0],"ix":2},"a":{"a":0,"k":[0,0],"ix":1},"s":{"a":0,"k":[20,20],"ix":3},"r":{"a":0,"k":0,"ix":6},"o":{"a":0,"k":100,"ix":7},"sk":{"a":0,"k":0,"ix":4},"sa":{"a":0,"k":0,"ix":5},"nm":"变换"}],"nm":"椭圆 1","np":3,"cix":2,"ix":1,"mn":"ADBE Vector Group"}],"ip":0,"op":500,"st":0,"bm":0,"sr":1}]}